odoo/addons/sale_order_line_price_history/README.rst
odoo/addons/sale_order_line_price_history/__init__.py
odoo/addons/sale_order_line_price_history/__manifest__.py
odoo/addons/sale_order_line_price_history/i18n/de.po
odoo/addons/sale_order_line_price_history/i18n/es.po
odoo/addons/sale_order_line_price_history/i18n/sale_order_line_price_history.pot
odoo/addons/sale_order_line_price_history/readme/CONTRIBUTORS.rst
odoo/addons/sale_order_line_price_history/readme/DESCRIPTION.rst
odoo/addons/sale_order_line_price_history/readme/ROADMAP.rst
odoo/addons/sale_order_line_price_history/readme/USAGE.rst
odoo/addons/sale_order_line_price_history/static/description/icon.png
odoo/addons/sale_order_line_price_history/static/description/index.html
odoo/addons/sale_order_line_price_history/tests/__init__.py
odoo/addons/sale_order_line_price_history/tests/test_sale_order_line_price_history.py
odoo/addons/sale_order_line_price_history/views/sale_views.xml
odoo/addons/sale_order_line_price_history/wizards/__init__.py
odoo/addons/sale_order_line_price_history/wizards/sale_orderLine_price_history.py
odoo/addons/sale_order_line_price_history/wizards/sale_orderLine_price_history.xml
odoo11_addon_sale_order_line_price_history-11.0.1.0.1.dist-info/METADATA
odoo11_addon_sale_order_line_price_history-11.0.1.0.1.dist-info/WHEEL
odoo11_addon_sale_order_line_price_history-11.0.1.0.1.dist-info/top_level.txt
odoo11_addon_sale_order_line_price_history-11.0.1.0.1.dist-info/RECORD
